migt/__init__.py
migt/mi.py
migt/splitter.py
migt/utils.py
migt-1.1.1.dist-info/METADATA
migt-1.1.1.dist-info/WHEEL
migt-1.1.1.dist-info/top_level.txt
migt-1.1.1.dist-info/RECORD
