Metadata-Version: 2.4
Name: migt
Version: 1.1.1
Summary: Model-agnostic dataset partitioning using Mutual Information
Author-email: Lida Shahmiri <lida_shahmiri@yahoo.co.uk>
License: MIT
Project-URL: Homepage, https://github.com/LShahmiri/MIGT-Splitter
Project-URL: Repository, https://github.com/LShahmiri/MIGT-Splitter
Project-URL: Issues, https://github.com/LShahmiri/MIGT-Splitter/issues
Project-URL: Paper, https://ieeexplore.ieee.org/abstract/document/10053008
Keywords: mutual-information,information-theory,dataset-partitioning,machine-learning,computer-vision
Classifier: Development Status :: 4 - Beta
Classifier: Intended Audience :: Science/Research
Classifier: License :: OSI Approved :: MIT License
Classifier: Operating System :: OS Independent
Classifier: Programming Language :: Python :: 3
Classifier: Programming Language :: Python :: 3.8
Classifier: Programming Language :: Python :: 3.9
Classifier: Programming Language :: Python :: 3.10
Classifier: Programming Language :: Python :: 3.11
Classifier: Topic :: Scientific/Engineering :: Artificial Intelligence
Classifier: Topic :: Scientific/Engineering :: Information Analysis
Classifier: Topic :: Software Development :: Libraries :: Python Modules
Requires-Python: >=3.8
Requires-Dist: numpy>=1.23
Requires-Dist: scikit-learn>=1.2
Requires-Dist: scikit-image>=0.19
Requires-Dist: opencv-python>=4.5
Requires-Dist: pillow>=9.0
Requires-Dist: tqdm>=4.64
